flight_status/__init__.py
flight_status/airlines.py
flight_status/handler/__init__.py
flight_status/handler/web_controller.py
flight_status/handler/air_asia/__init__.py
flight_status/handler/air_asia/scraper.py
flight_status/handler/indigo/__init__.py
flight_status/handler/indigo/scraper.py
flight_status/handler/spice_jet/__init__.py
flight_status/handler/spice_jet/scraper.py
flight_status-1.0.1.dist-info/LICENSE.txt
flight_status-1.0.1.dist-info/METADATA
flight_status-1.0.1.dist-info/WHEEL
flight_status-1.0.1.dist-info/top_level.txt
flight_status-1.0.1.dist-info/RECORD
