Metadata-Version: 2.1
Name: flight-status
Version: 1.0.1
Summary: PIP package to get status of flight pnr status and other details [Indian Airlines]
Home-page: https://github.com/tiwari85aman/flight-status.git
Author: Aman Tiwari, Shibani Mahapatra
Author-email: tiwari.aman85@gmail.com, shibani.mahapatra47@gmail.com
License: MIT
Download-URL: https://pypi.org/project/flight-status/
Keywords: Flight,PNR,Pnr status,India,Airlines
Platform: UNKNOWN
Classifier: Programming Language :: Python
Classifier: Programming Language :: Python :: 3
Classifier: Programming Language :: Python :: 3.6
Classifier: Programming Language :: Python :: 3.7
Classifier: Programming Language :: Python :: 3.8
Classifier: Intended Audience :: Developers
Classifier: License :: OSI Approved :: MIT License
Requires-Python: >=2.7.0
Requires-Dist: beautifulsoup4 (<=4.9.1)
Requires-Dist: selenium (<=3.141.0)
